serde_timedelta/__init__.py
serde_timedelta/py.typed
pyserde_timedelta-0.1.1.dist-info/LICENSE
pyserde_timedelta-0.1.1.dist-info/METADATA
pyserde_timedelta-0.1.1.dist-info/WHEEL
pyserde_timedelta-0.1.1.dist-info/RECORD
