Metadata-Version: 2.1
Name: pyserde-timedelta
Version: 0.1.1
Summary: pyserde extension for (de)serializing timedelta
Home-page: https://github.com/yukinarit/pyserde-timedelta
License: MIT
Author: yukinarit
Author-email: yukinarit84@gmail.com
Requires-Python: >=3.8,<4.0
Classifier: Development Status :: 5 - Production/Stable
Classifier: Intended Audience :: Developers
Classifier: License :: OSI Approved :: MIT License
Classifier: Programming Language :: Python :: 3
Classifier: Programming Language :: Python :: 3.8
Classifier: Programming Language :: Python :: 3.9
Classifier: Programming Language :: Python :: 3.10
Classifier: Programming Language :: Python :: 3.11
Classifier: Programming Language :: Python :: 3.12
Classifier: Programming Language :: Python :: Implementation :: CPython
Classifier: Programming Language :: Python :: Implementation :: PyPy
Requires-Dist: isodate (>=0.6,<0.7)
Requires-Dist: plum-dispatch (>=2.2,<3.0)
Requires-Dist: pyserde (>=0.13)
Project-URL: Repository, https://github.com/yukinarit/pyserde-timedelta
